yolov5detect/__init__.py
yolov5detect/annotation.py
yolov5detect/detect.py
yolov5detect/reader.py
yolov5detect/deep_sort/__init__.py
yolov5detect/deep_sort/deep_sort.py
yolov5detect/deep_sort/deep/__init__.py
yolov5detect/deep_sort/deep/reid/__init__.py
yolov5detect/deep_sort/deep/reid/torchreid/__init__.py
yolov5detect/deep_sort/deep/reid/torchreid/models/__init__.py
yolov5detect/deep_sort/deep/reid/torchreid/models/densenet.py
yolov5detect/deep_sort/deep/reid/torchreid/models/hacnn.py
yolov5detect/deep_sort/deep/reid/torchreid/models/inceptionresnetv2.py
yolov5detect/deep_sort/deep/reid/torchreid/models/inceptionv4.py
yolov5detect/deep_sort/deep/reid/torchreid/models/mlfn.py
yolov5detect/deep_sort/deep/reid/torchreid/models/mobilenetv2.py
yolov5detect/deep_sort/deep/reid/torchreid/models/mudeep.py
yolov5detect/deep_sort/deep/reid/torchreid/models/nasnet.py
yolov5detect/deep_sort/deep/reid/torchreid/models/osnet.py
yolov5detect/deep_sort/deep/reid/torchreid/models/osnet_ain.py
yolov5detect/deep_sort/deep/reid/torchreid/models/pcb.py
yolov5detect/deep_sort/deep/reid/torchreid/models/resnet.py
yolov5detect/deep_sort/deep/reid/torchreid/models/resnet_ibn_a.py
yolov5detect/deep_sort/deep/reid/torchreid/models/resnet_ibn_b.py
yolov5detect/deep_sort/deep/reid/torchreid/models/resnetmid.py
yolov5detect/deep_sort/deep/reid/torchreid/models/senet.py
yolov5detect/deep_sort/deep/reid/torchreid/models/shufflenet.py
yolov5detect/deep_sort/deep/reid/torchreid/models/shufflenetv2.py
yolov5detect/deep_sort/deep/reid/torchreid/models/squeezenet.py
yolov5detect/deep_sort/deep/reid/torchreid/models/xception.py
yolov5detect/deep_sort/deep/reid/torchreid/utils/__init__.py
yolov5detect/deep_sort/deep/reid/torchreid/utils/avgmeter.py
yolov5detect/deep_sort/deep/reid/torchreid/utils/feature_extractor.py
yolov5detect/deep_sort/deep/reid/torchreid/utils/loggers.py
yolov5detect/deep_sort/deep/reid/torchreid/utils/model_complexity.py
yolov5_detect-0.1.21.dist-info/LICENSE
yolov5_detect-0.1.21.dist-info/METADATA
yolov5_detect-0.1.21.dist-info/WHEEL
yolov5_detect-0.1.21.dist-info/top_level.txt
yolov5_detect-0.1.21.dist-info/RECORD
