Metadata-Version: 2.1
Name: yolov5-detect
Version: 0.1.21
Summary: simple yolov5 wrapper for detect(onnx, dnn, openvino)
Home-page: https://github.com/2432001677/yolov5-detect
Author: Bruce Yu
Author-email: bruceyufox@foxmail.com
License: GPLv3+
Platform: UNKNOWN
Classifier: Programming Language :: Python :: 3
Classifier: License :: OSI Approved :: GNU General Public License v3 or later (GPLv3+)
Classifier: Operating System :: OS Independent
Requires-Python: >=3.6
License-File: LICENSE
